classyjson/__init__.py
classyjson/types.py
classy_json-3.2.1.dist-info/LICENSE
classy_json-3.2.1.dist-info/WHEEL
classy_json-3.2.1.dist-info/METADATA
classy_json-3.2.1.dist-info/RECORD
