Metadata-Version: 2.1
Name: classy-json
Version: 3.2.1
Summary: Dot-access for Python dictionaries like JS!
Home-page: https://github.com/Iapetus-11/Classy-JSON
License: MIT
Keywords: json,dot-access,dot access,js,javascript
Author: Milo Weinberg
Author-email: iapetus011@gmail.com
Requires-Python: >=3.7.3,<4.0.0
Classifier: License :: OSI Approved :: MIT License
Classifier: Programming Language :: Python :: 3
Classifier: Programming Language :: Python :: 3.8
Classifier: Programming Language :: Python :: 3.9
Project-URL: Repository, https://github.com/Iapetus-11/Classy-JSON
